bph_co2/__init__.py
bph_co2/ambient.py
bph_co2/solver.py
bph_co2/timeseries.py
bph_co2/tools.py
bph_co2/ventilation.py
bph_co2/wall.py
bph_co2/window.py
bph_co2/zone.py
bph_co2/resources/__init__.py
bph_co2/resources/Input_Data/__init__.py
bph_co2/resources/Input_Data/air_change_rate.csv
bph_co2/resources/Input_Data/indoor_temperature.csv
bph_co2/resources/Input_Data/internal_co2_source.csv
bph_co2/resources/Input_Data/internal_heat_source.csv
bph_co2/resources/Input_Data/outdoor_temperature.csv
bph_co2/resources/Input_Data/persons.csv
bph_co2/resources/Input_Data/room_heating.csv
bph_co2/resources/Input_Data/window_open.csv
bph_co2/resources/Input_Data/window_state.csv
bph2_co2-1.0.4.dist-info/LICENSE.txt
bph2_co2-1.0.4.dist-info/METADATA
bph2_co2-1.0.4.dist-info/WHEEL
bph2_co2-1.0.4.dist-info/entry_points.txt
bph2_co2-1.0.4.dist-info/top_level.txt
bph2_co2-1.0.4.dist-info/RECORD
